covsirphy/__citation__.py
covsirphy/__init__.py
covsirphy/__version__.py
covsirphy/downloading/__init__.py
covsirphy/downloading/_db.py
covsirphy/downloading/_db_covid19dh.py
covsirphy/downloading/_db_cs_japan.py
covsirphy/downloading/_db_owid.py
covsirphy/downloading/_db_wpp.py
covsirphy/downloading/_provider.py
covsirphy/downloading/downloader.py
covsirphy/dynamics/__init__.py
covsirphy/dynamics/_simulator.py
covsirphy/dynamics/_trend.py
covsirphy/dynamics/dynamics.py
covsirphy/dynamics/ode.py
covsirphy/dynamics/sewirf.py
covsirphy/dynamics/sir.py
covsirphy/dynamics/sird.py
covsirphy/dynamics/sirf.py
covsirphy/engineering/__init__.py
covsirphy/engineering/_cleaner.py
covsirphy/engineering/_complement.py
covsirphy/engineering/_transformer.py
covsirphy/engineering/engineer.py
covsirphy/gis/__init__.py
covsirphy/gis/_choropleth.py
covsirphy/gis/_geometry.py
covsirphy/gis/_layer.py
covsirphy/gis/_subset.py
covsirphy/gis/gis.py
covsirphy/science/__init__.py
covsirphy/science/_autots.py
covsirphy/science/ml.py
covsirphy/science/ode_scenario.py
covsirphy/util/__init__.py
covsirphy/util/alias.py
covsirphy/util/config.py
covsirphy/util/error.py
covsirphy/util/evaluator.py
covsirphy/util/filer.py
covsirphy/util/stopwatch.py
covsirphy/util/term.py
covsirphy/util/validator.py
covsirphy/visualization/__init__.py
covsirphy/visualization/bar_plot.py
covsirphy/visualization/compare_plot.py
covsirphy/visualization/line_plot.py
covsirphy/visualization/scatter_plot.py
covsirphy/visualization/vbase.py
covsirphy-3.1.2.dist-info/LICENSE
covsirphy-3.1.2.dist-info/METADATA
covsirphy-3.1.2.dist-info/WHEEL
covsirphy-3.1.2.dist-info/RECORD
