Metadata-Version: 2.1
Name: covsirphy
Version: 3.1.2
Summary: COVID-19 data analysis with phase-dependent SIR-derived ODE models
Home-page: https://github.com/lisphilar/covid19-sir/
License: Apache-2.0
Keywords: covid19,covid,data engineering,data science
Author: Hirokazu Takaya
Author-email: lisphilar@outlook.jp
Requires-Python: >=3.9,<3.13
Classifier: Development Status :: 5 - Production/Stable
Classifier: License :: OSI Approved :: Apache Software License
Classifier: Programming Language :: Python :: 3
Classifier: Programming Language :: Python :: 3.9
Classifier: Programming Language :: Python :: 3.10
Classifier: Programming Language :: Python :: 3.11
Classifier: Programming Language :: Python :: 3.12
Classifier: Topic :: Scientific/Engineering
Requires-Dist: AutoTS (>=0.6.10,<0.7.0)
Requires-Dist: Unidecode (>=1.3.8,<2.0.0)
Requires-Dist: country-converter (>=1.2.0,<2.0.0)
Requires-Dist: geopandas (>=0.14.3,<1.1.0)
Requires-Dist: loguru (>=0.7.2,<0.8.0)
Requires-Dist: matplotlib (>=3.8.2,<4.0.0)
Requires-Dist: numpy (>=1.26.3,<3.0.0)
Requires-Dist: optuna (>=3.5.0,<4.0.0)
Requires-Dist: p-tqdm (>=1.4.0,<2.0.0)
Requires-Dist: pandas (>=2.2.0,<3.0.0)
Requires-Dist: pca (>=2.0.5,<3.0.0)
Requires-Dist: pyarrow (>=15,<18)
Requires-Dist: requests (>=2.31.0,<3.0.0)
Requires-Dist: ruptures (>=1.1.9,<2.0.0)
Requires-Dist: scipy (>=1.12.0,<2.0.0)
Requires-Dist: tabulate (>=0.9.0,<0.10.0)
Requires-Dist: typing-extensions (>=4.9.0,<5.0.0)
Project-URL: Documentation, https://lisphilar.github.io/covid19-sir/
Project-URL: Repository, https://github.com/lisphilar/covid19-sir/
